client/__init__.py
client/client.py
client/connection.py
client/exceptions.py
client/resource.py
client/api/__init__.py
client/api/blocks.py
client/api/delegates.py
client/api/locks.py
client/api/node.py
client/api/peers.py
client/api/rounds.py
client/api/transactions.py
client/api/votes.py
client/api/wallets.py
arkecosystem_client-2.0.0.dist-info/LICENSE
arkecosystem_client-2.0.0.dist-info/METADATA
arkecosystem_client-2.0.0.dist-info/WHEEL
arkecosystem_client-2.0.0.dist-info/top_level.txt
arkecosystem_client-2.0.0.dist-info/RECORD
