Metadata-Version: 2.1
Name: arkecosystem-client
Version: 2.0.0
Summary: A simple Python API client for the ARK Blockchain.
Home-page: https://github.com/ArkEcosystem/python-client
Author: Ark Ecosystem
Author-email: info@client.io
License: UNKNOWN
Platform: UNKNOWN
Requires-Dist: requests (>=2.19.1)
Requires-Dist: backoff (>=1.6.0)
Requires-Dist: flatten-dict (>=0.3.0)
Provides-Extra: dev
Requires-Dist: requests (>=2.19.1) ; extra == 'dev'
Requires-Dist: backoff (>=1.6.0) ; extra == 'dev'
Requires-Dist: flatten-dict (>=0.3.0) ; extra == 'dev'
Requires-Dist: flake8 (>=3.5.0) ; extra == 'dev'
Requires-Dist: flake8-import-order (>=0.17.1) ; extra == 'dev'
Requires-Dist: flake8-print (>=3.1.0) ; extra == 'dev'
Requires-Dist: flake8-quotes (>=1.0.0) ; extra == 'dev'
Requires-Dist: pytest (>=3.6.1) ; extra == 'dev'
Requires-Dist: pytest-responses (>=0.3.0) ; extra == 'dev'
Requires-Dist: pytest-mock (>=1.10.0) ; extra == 'dev'
Requires-Dist: pytest-cov (>=2.5.1) ; extra == 'dev'
Provides-Extra: test
Requires-Dist: flake8 (>=3.5.0) ; extra == 'test'
Requires-Dist: flake8-import-order (>=0.17.1) ; extra == 'test'
Requires-Dist: flake8-print (>=3.1.0) ; extra == 'test'
Requires-Dist: flake8-quotes (>=1.0.0) ; extra == 'test'
Requires-Dist: pytest (>=3.6.1) ; extra == 'test'
Requires-Dist: pytest-responses (>=0.3.0) ; extra == 'test'
Requires-Dist: pytest-mock (>=1.10.0) ; extra == 'test'
Requires-Dist: pytest-cov (>=2.5.1) ; extra == 'test'
